odoo/addons/sale_down_payment_wizard_taxes/README.rst
odoo/addons/sale_down_payment_wizard_taxes/__init__.py
odoo/addons/sale_down_payment_wizard_taxes/__manifest__.py
odoo/addons/sale_down_payment_wizard_taxes/i18n/sale_down_payment_wizard_taxes.pot
odoo/addons/sale_down_payment_wizard_taxes/readme/CONTRIBUTORS.rst
odoo/addons/sale_down_payment_wizard_taxes/readme/DESCRIPTION.rst
odoo/addons/sale_down_payment_wizard_taxes/readme/USAGE.rst
odoo/addons/sale_down_payment_wizard_taxes/static/description/icon.png
odoo/addons/sale_down_payment_wizard_taxes/static/description/index.html
odoo/addons/sale_down_payment_wizard_taxes/tests/__init__.py
odoo/addons/sale_down_payment_wizard_taxes/tests/test_sale_down_payment_wizard_taxes.py
odoo/addons/sale_down_payment_wizard_taxes/views/sale_make_invoice_advance_views.xml
odoo/addons/sale_down_payment_wizard_taxes/wizards/__init__.py
odoo/addons/sale_down_payment_wizard_taxes/wizards/sale_advance_payment_inv.py
odoo13_addon_sale_down_payment_wizard_taxes-13.0.1.0.1.dist-info/METADATA
odoo13_addon_sale_down_payment_wizard_taxes-13.0.1.0.1.dist-info/WHEEL
odoo13_addon_sale_down_payment_wizard_taxes-13.0.1.0.1.dist-info/top_level.txt
odoo13_addon_sale_down_payment_wizard_taxes-13.0.1.0.1.dist-info/RECORD
